[{"repo_name": "spring-boot", "repo_url": "spring-projects/spring-boot", "issue_html_url": "https://github.com/spring-projects/spring-boot/issues/143", "earliest_issue_date": "2013-12-04T16:45:14Z", "fix_commit_hash": "8fe696944a29f12f5a465a794f0544dc06cce27d", "tipo": "Commit", "commit_author": "Dave Syer", "commiter": "Dave Syer", "commit_date": "2014-01-06T17:28:22+00:00", "committer_data": "2014-01-06T17:28:22+00:00", "changed_files": 1, "deletions": 3, "insertions": 9, "lines": 12, "dmm_unit_size": 1.0, "dmm_unit_complexity": 1.0, "dmm_unit_interfacing": 1.0, "files_exts": ["java"], "inducing_commit_hash_pyszz": ["1bec676ca1f56b66c5ae54b70d20981b1c8a20f5"], "inducing_commit_hash_pd": ["5e4238f38a4fd785c6a04dd11f23f49fdff2c286"]}, {"repo_name": "spring-boot", "repo_url": "spring-projects/spring-boot", "issue_html_url": "https://github.com/spring-projects/spring-boot/issues/141", "earliest_issue_date": "2013-12-03T22:35:24Z", "fix_commit_hash": "2433f721bca2082c8cba0dc29870dffc9a659f30", "tipo": "Commit", "commit_author": "Dave Syer", "commiter": "Dave Syer", "commit_date": "2014-06-18T16:02:26+01:00", "committer_data": "2014-06-18T16:06:09+01:00", "changed_files": 6, "deletions": 7, "insertions": 233, "lines": 240, "dmm_unit_size": 0.6, "dmm_unit_complexity": 0.8428571428571429, "dmm_unit_interfacing": 1.0, "files_exts": ["java", "gradle", "gradle", "groovy", "java", "java"], "inducing_commit_hash_pyszz": [], "inducing_commit_hash_pd": []}, {"repo_name": "spring-boot", "repo_url": "spring-projects/spring-boot", "issue_html_url": "https://github.com/spring-projects/spring-boot/issues/139", "earliest_issue_date": "2013-12-02T13:12:06Z", "fix_commit_hash": "f39b044cf78b84077dcf205cc205f48804480ae6", "tipo": "Commit", "commit_author": "Dave Syer", "commiter": "Dave Syer", "commit_date": "2013-12-02T14:10:56+00:00", "committer_data": "2013-12-02T14:10:56+00:00", "changed_files": 2, "deletions": 1, "insertions": 5, "lines": 6, "dmm_unit_size": 0.0, "dmm_unit_complexity": 1.0, "dmm_unit_interfacing": 0.0, "files_exts": ["java", "java"], "inducing_commit_hash_pyszz": [], "inducing_commit_hash_pd": ["5e4238f38a4fd785c6a04dd11f23f49fdff2c286"]}, {"repo_name": "spring-boot", "repo_url": "spring-projects/spring-boot", "issue_html_url": "https://github.com/spring-projects/spring-boot/issues/136", "earliest_issue_date": "2013-11-26T23:04:24Z", "fix_commit_hash": "f1026b120202d80f18ca80342a501faedc8539c0", "tipo": "Commit", "commit_author": "Dave Syer", "commiter": "Dave Syer", "commit_date": "2013-11-29T10:12:08+00:00", "committer_data": "2013-11-29T10:12:08+00:00", "changed_files": 3, "deletions": 35, "insertions": 175, "lines": 210, "dmm_unit_size": 0.0, "dmm_unit_complexity": 0.0, "dmm_unit_interfacing": 0.3148148148148148, "files_exts": ["java", "java", "java"], "inducing_commit_hash_pyszz": ["820f43d3bc7fb1aa1f257cccea3c7969d7627bbf"], "inducing_commit_hash_pd": ["6ab14a51eb4eda929bbd8231025e87b782b11ab5", "b19f6bb238cd25b416ecb1c6e1c1993372c335f1", "820f43d3bc7fb1aa1f257cccea3c7969d7627bbf"]}, {"repo_name": "spring-boot", "repo_url": "spring-projects/spring-boot", "issue_html_url": "https://github.com/spring-projects/spring-boot/issues/126", "earliest_issue_date": "2013-11-19T16:13:36Z", "fix_commit_hash": "618bfc65aca395c759d43be626979e2662455904", "tipo": "Commit", "commit_author": "Phillip Webb", "commiter": "Phillip Webb", "commit_date": "2014-01-20T22:28:24-08:00", "committer_data": "2014-01-20T22:28:24-08:00", "changed_files": 1, "deletions": 1, "insertions": 1, "lines": 2, "dmm_unit_size": null, "dmm_unit_complexity": null, "dmm_unit_interfacing": null, "files_exts": ["xml"], "inducing_commit_hash_pyszz": [], "inducing_commit_hash_pd": []}, {"repo_name": "spring-boot", "repo_url": "spring-projects/spring-boot", "issue_html_url": "https://github.com/spring-projects/spring-boot/issues/120", "earliest_issue_date": "2013-11-17T12:10:18Z", "fix_commit_hash": "71fd474ed2d742e82cdc89332172e94664fc14ef", "tipo": "Commit", "commit_author": "Dave Syer", "commiter": "Dave Syer", "commit_date": "2013-11-18T09:59:11+00:00", "committer_data": "2013-11-18T09:59:11+00:00", "changed_files": 2, "deletions": 1, "insertions": 17, "lines": 18, "dmm_unit_size": 1.0, "dmm_unit_complexity": 1.0, "dmm_unit_interfacing": 1.0, "files_exts": ["java", "java"], "inducing_commit_hash_pyszz": ["345c0fc5a490cc792559eab4c42cbc2e7739e729"], "inducing_commit_hash_pd": ["345c0fc5a490cc792559eab4c42cbc2e7739e729"]}, {"repo_name": "spring-boot", "repo_url": "spring-projects/spring-boot", "issue_html_url": "https://github.com/spring-projects/spring-boot/issues/119", "earliest_issue_date": "2013-11-16T00:58:53Z", "fix_commit_hash": "17de6689ab43b6d8fc8b60b87eb1155ba55b26f6", "tipo": "Commit", "commit_author": "Dave Syer", "commiter": "Dave Syer", "commit_date": "2013-11-17T15:29:12+00:00", "committer_data": "2013-11-17T15:29:12+00:00", "changed_files": 1, "deletions": 3, "insertions": 9, "lines": 12, "dmm_unit_size": null, "dmm_unit_complexity": null, "dmm_unit_interfacing": null, "files_exts": ["java"], "inducing_commit_hash_pyszz": ["0e798a32aaafe859d1e01495578b0c527421dc73"], "inducing_commit_hash_pd": ["e60efc7e55933d22ac5d614fd59af64aacabdb5f"]}, {"repo_name": "spring-boot", "repo_url": "spring-projects/spring-boot", "issue_html_url": "https://github.com/spring-projects/spring-boot/issues/3647", "earliest_issue_date": "2015-08-03T08:45:09Z", "fix_commit_hash": "15442b9667ad2f047d06737f9aa2a70a5b02f1b3", "tipo": "Commit", "commit_author": "Stephane Nicoll", "commiter": "Stephane Nicoll", "commit_date": "2015-08-03T10:46:33+02:00", "committer_data": "2015-08-03T10:46:33+02:00", "changed_files": 1, "deletions": 1, "insertions": 1, "lines": 2, "dmm_unit_size": null, "dmm_unit_complexity": null, "dmm_unit_interfacing": null, "files_exts": ["java"], "inducing_commit_hash_pyszz": ["1e464da2480568014a87dd0bac6febe63a76c889"], "inducing_commit_hash_pd": ["ef39634e302748f3473aec6468cb7d06df92ced2"]}, {"repo_name": "spring-boot", "repo_url": "spring-projects/spring-boot", "issue_html_url": "https://github.com/spring-projects/spring-boot/issues/3643", "earliest_issue_date": "2015-08-02T14:31:27Z", "fix_commit_hash": "9fcc860908010fa34ce588b833247aa2715d9d9f", "tipo": "Commit", "commit_author": "Andy Wilkinson", "commiter": "Andy Wilkinson", "commit_date": "2015-08-06T12:05:56+01:00", "committer_data": "2015-08-06T12:06:39+01:00", "changed_files": 3, "deletions": 3, "insertions": 32, "lines": 35, "dmm_unit_size": 1.0, "dmm_unit_complexity": 1.0, "dmm_unit_interfacing": 1.0, "files_exts": ["java", "java", "java"], "inducing_commit_hash_pyszz": ["789e75d2e51dca38d386c0f5fb7687c7637ea7be"], "inducing_commit_hash_pd": ["7e3cb50a22eb0e782226d831ec09c223f757f72c"]}, {"repo_name": "spring-boot", "repo_url": "spring-projects/spring-boot", "issue_html_url": "https://github.com/spring-projects/spring-boot/issues/3642", "earliest_issue_date": "2015-08-02T13:12:18Z", "fix_commit_hash": "65efd1725f4184cb9720ed3eadb3a351a9f7f190", "tipo": "Commit", "commit_author": "Stephane Nicoll", "commiter": "Stephane Nicoll", "commit_date": "2015-08-05T15:35:47+02:00", "committer_data": "2015-08-05T15:35:47+02:00", "changed_files": 1, "deletions": 0, "insertions": 2, "lines": 2, "dmm_unit_size": null, "dmm_unit_complexity": null, "dmm_unit_interfacing": null, "files_exts": ["java"], "inducing_commit_hash_pyszz": [], "inducing_commit_hash_pd": []}]