[{"repo_name": "spring-boot", "repo_url": "spring-projects/spring-boot", "issue_html_url": "https://github.com/spring-projects/spring-boot/issues/611", "earliest_issue_date": "2014-03-31T18:55:34Z", "fix_commit_hash": "ed3fc06d811415063161bd4023e3978fa2a26d90", "tipo": "Commit", "commit_author": "Phillip Webb", "commiter": "Phillip Webb", "commit_date": "2014-03-31T17:28:14-07:00", "committer_data": "2014-03-31T17:28:14-07:00", "changed_files": 1, "deletions": 9, "insertions": 0, "lines": 9, "dmm_unit_size": 0.6, "dmm_unit_complexity": 0.0, "dmm_unit_interfacing": 0.0, "files_exts": ["java"], "inducing_commit_hash_pyszz": ["18a666caf881bd4bb9e14216be90bfc47930ba27"], "inducing_commit_hash_pd": ["18a666caf881bd4bb9e14216be90bfc47930ba27", "d950d15f9b121ef1c0c4948543dc3d4836f66c4f"]}, {"repo_name": "spring-boot", "repo_url": "spring-projects/spring-boot", "issue_html_url": "https://github.com/spring-projects/spring-boot/issues/610", "earliest_issue_date": "2014-03-31T18:55:08Z", "fix_commit_hash": "35b1a59bbd755f555924c183946a088442d98c70", "tipo": "Commit", "commit_author": "Phillip Webb", "commiter": "Phillip Webb", "commit_date": "2014-03-31T17:25:59-07:00", "committer_data": "2014-03-31T17:25:59-07:00", "changed_files": 1, "deletions": 9, "insertions": 34, "lines": 43, "dmm_unit_size": 0.0, "dmm_unit_complexity": 1.0, "dmm_unit_interfacing": 1.0, "files_exts": ["java"], "inducing_commit_hash_pyszz": ["18a666caf881bd4bb9e14216be90bfc47930ba27"], "inducing_commit_hash_pd": ["18a666caf881bd4bb9e14216be90bfc47930ba27", "bd73705393644e7fca2227795fae6b82e23101cd", "fb6b2244707dd5dfad12d62cb6a3c396555270d1"]}, {"repo_name": "spring-boot", "repo_url": "spring-projects/spring-boot", "issue_html_url": "https://github.com/spring-projects/spring-boot/issues/601", "earliest_issue_date": "2014-03-29T01:00:28Z", "fix_commit_hash": "499f54893b88f32bfe59f951de647200f4285e2d", "tipo": "Commit", "commit_author": "Dave Syer", "commiter": "Phillip Webb", "commit_date": "2014-03-31T09:21:07+01:00", "committer_data": "2014-03-31T17:33:39-07:00", "changed_files": 1, "deletions": 0, "insertions": 4, "lines": 4, "dmm_unit_size": null, "dmm_unit_complexity": null, "dmm_unit_interfacing": null, "files_exts": ["java"], "inducing_commit_hash_pyszz": [], "inducing_commit_hash_pd": []}, {"repo_name": "spring-boot", "repo_url": "spring-projects/spring-boot", "issue_html_url": "https://github.com/spring-projects/spring-boot/issues/599", "earliest_issue_date": "2014-03-27T18:06:43Z", "fix_commit_hash": "aca67066bf0e5dc72d5864cf3dc842ec2e53d724", "tipo": "Commit", "commit_author": "Phillip Webb", "commiter": "Phillip Webb", "commit_date": "2014-03-27T11:04:20-07:00", "committer_data": "2014-03-27T11:22:03-07:00", "changed_files": 24, "deletions": 127, "insertions": 140, "lines": 267, "dmm_unit_size": 1.0, "dmm_unit_complexity": 1.0, "dmm_unit_interfacing": 1.0, "files_exts": ["adoc", "java", "java", "java", "java", "java", "java", "java", "java", "java", "java", "java", "java", "java", "java", "java", "java", "java", "java", "java", "java", "java", "java", "java"], "inducing_commit_hash_pyszz": ["d117a6b22b07d5013156895d3611b25346cc78b9"], "inducing_commit_hash_pd": ["80ac1fb0cd3ce75715a758ce41898f033cf8c66a", "4c14f6f68550c3c7b0b3760ab8599f58559c6752", "9504f6e5a92754e398daa4ba0298b69aaa44bdba", "7a285cf65d87eb842e2f979545daca02aaf46252", "6c5f9a596173bcf59f316d34f3312b93691d1971", "5501adc862fdee48f6322a579f98427d4b1431ac", "d117a6b22b07d5013156895d3611b25346cc78b9"]}, {"repo_name": "spring-boot", "repo_url": "spring-projects/spring-boot", "issue_html_url": "https://github.com/spring-projects/spring-boot/issues/598", "earliest_issue_date": "2014-03-27T17:19:14Z", "fix_commit_hash": "1deeccda30aea40040679102b1686ab8ca066f59", "tipo": "Commit", "commit_author": "Andy Wilkinson", "commiter": "Andy Wilkinson", "commit_date": "2014-05-21T13:58:13+01:00", "committer_data": "2014-05-21T13:58:44+01:00", "changed_files": 1, "deletions": 8, "insertions": 1, "lines": 9, "dmm_unit_size": null, "dmm_unit_complexity": null, "dmm_unit_interfacing": null, "files_exts": ["java"], "inducing_commit_hash_pyszz": ["46fc5c05e32b757c0d95eb13d4a592aa06593af3"], "inducing_commit_hash_pd": ["46fc5c05e32b757c0d95eb13d4a592aa06593af3"]}, {"repo_name": "spring-boot", "repo_url": "spring-projects/spring-boot", "issue_html_url": "https://github.com/spring-projects/spring-boot/issues/596", "earliest_issue_date": "2014-03-27T16:44:35Z", "fix_commit_hash": "71c2c69c9224c8998c69e0d75e6285b586c24b12", "tipo": "Commit", "commit_author": "Dave Syer", "commiter": "Dave Syer", "commit_date": "2014-03-27T17:22:04+00:00", "committer_data": "2014-03-27T17:23:47+00:00", "changed_files": 4, "deletions": 7, "insertions": 17, "lines": 24, "dmm_unit_size": 1.0, "dmm_unit_complexity": 1.0, "dmm_unit_interfacing": 1.0, "files_exts": ["java", "java", "java", "java"], "inducing_commit_hash_pyszz": ["13e040c06e18021e4ba081dcb0d0d68e58b03274"], "inducing_commit_hash_pd": ["13e040c06e18021e4ba081dcb0d0d68e58b03274", "521174754e57106af154df4de1c77e1d3c14d1dc", "bbac4ea9fb5a49c9e8e2a38f424882c6bde04789", "5501adc862fdee48f6322a579f98427d4b1431ac", "fb6b2244707dd5dfad12d62cb6a3c396555270d1"]}, {"repo_name": "spring-boot", "repo_url": "spring-projects/spring-boot", "issue_html_url": "https://github.com/spring-projects/spring-boot/issues/594", "earliest_issue_date": "2014-03-27T15:01:50Z", "fix_commit_hash": "46fc5c05e32b757c0d95eb13d4a592aa06593af3", "tipo": "Commit", "commit_author": "Andy Wilkinson", "commiter": "Andy Wilkinson", "commit_date": "2014-03-27T16:20:29+00:00", "committer_data": "2014-03-27T16:49:37+00:00", "changed_files": 1, "deletions": 1, "insertions": 8, "lines": 9, "dmm_unit_size": null, "dmm_unit_complexity": null, "dmm_unit_interfacing": null, "files_exts": ["java"], "inducing_commit_hash_pyszz": ["bd73705393644e7fca2227795fae6b82e23101cd"], "inducing_commit_hash_pd": ["bd73705393644e7fca2227795fae6b82e23101cd"]}, {"repo_name": "spring-boot", "repo_url": "spring-projects/spring-boot", "issue_html_url": "https://github.com/spring-projects/spring-boot/issues/591", "earliest_issue_date": "2014-03-27T04:00:39Z", "fix_commit_hash": "b75894aec218a045bd91652840f07f0aecf01a73", "tipo": "Commit", "commit_author": "Phillip Webb", "commiter": "Phillip Webb", "commit_date": "2014-03-26T21:33:52-07:00", "committer_data": "2014-03-26T21:33:52-07:00", "changed_files": 1, "deletions": 1, "insertions": 1, "lines": 2, "dmm_unit_size": null, "dmm_unit_complexity": null, "dmm_unit_interfacing": null, "files_exts": ["java"], "inducing_commit_hash_pyszz": ["bae26e2c0780d6fbbddb615bdd3da06d06b9cb96"], "inducing_commit_hash_pd": ["bae26e2c0780d6fbbddb615bdd3da06d06b9cb96"]}, {"repo_name": "spring-boot", "repo_url": "spring-projects/spring-boot", "issue_html_url": "https://github.com/spring-projects/spring-boot/issues/587", "earliest_issue_date": "2014-03-26T21:56:24Z", "fix_commit_hash": "126fedc14a7216fefde02d8eba264c35851b3edc", "tipo": "Commit", "commit_author": "Christian Dupuis", "commiter": "Christian Dupuis", "commit_date": "2014-05-06T13:32:29+02:00", "committer_data": "2014-05-06T13:32:29+02:00", "changed_files": 4, "deletions": 17, "insertions": 83, "lines": 100, "dmm_unit_size": 1.0, "dmm_unit_complexity": 1.0, "dmm_unit_interfacing": 0.8, "files_exts": ["java", "java", "java", "java"], "inducing_commit_hash_pyszz": ["0f85f31960b958f9a1fc32dc2a00185e96c02726"], "inducing_commit_hash_pd": ["d784cb6a8804af80699033ca29e09de1fb43d442", "6b599b8483e2fad1b679d937bf8de6d4eb269462", "0f85f31960b958f9a1fc32dc2a00185e96c02726"]}, {"repo_name": "spring-boot", "repo_url": "spring-projects/spring-boot", "issue_html_url": "https://github.com/spring-projects/spring-boot/issues/585", "earliest_issue_date": "2014-03-26T16:23:58Z", "fix_commit_hash": "bae26e2c0780d6fbbddb615bdd3da06d06b9cb96", "tipo": "Commit", "commit_author": "Dave Syer", "commiter": "Dave Syer", "commit_date": "2014-03-26T16:24:23+00:00", "committer_data": "2014-03-26T16:24:23+00:00", "changed_files": 5, "deletions": 31, "insertions": 55, "lines": 86, "dmm_unit_size": 1.0, "dmm_unit_complexity": 1.0, "dmm_unit_interfacing": 1.0, "files_exts": ["java", "xml", "xml", "xml", "java"], "inducing_commit_hash_pyszz": [], "inducing_commit_hash_pd": []}]