[{"repo_name": "spring-boot", "repo_url": "spring-projects/spring-boot", "issue_html_url": "https://github.com/spring-projects/spring-boot/issues/5700", "earliest_issue_date": "2016-04-15T09:05:22Z", "fix_commit_hash": "2e540780832143d9ceaf884da5846115baafed7b", "tipo": "Commit", "commit_author": "Andy Wilkinson", "commiter": "Andy Wilkinson", "commit_date": "2016-04-18T15:30:23+01:00", "committer_data": "2016-04-18T15:30:23+01:00", "changed_files": 1, "deletions": 1, "insertions": 3, "lines": 4, "dmm_unit_size": 1.0, "dmm_unit_complexity": 1.0, "dmm_unit_interfacing": 1.0, "files_exts": ["java"], "inducing_commit_hash_pyszz": ["3995c16ba60bbeb1933c2233ffcab368655fb3c2"]}, {"repo_name": "spring-boot", "repo_url": "spring-projects/spring-boot", "issue_html_url": "https://github.com/spring-projects/spring-boot/issues/5694", "earliest_issue_date": "2016-04-14T19:41:56Z", "fix_commit_hash": "5bc290eac6c02f62a769a15f73d8d16876fec4f3", "tipo": "Commit", "commit_author": "Stephane Nicoll", "commiter": "Stephane Nicoll", "commit_date": "2016-04-15T08:54:35+02:00", "committer_data": "2016-04-15T08:54:35+02:00", "changed_files": 1, "deletions": 0, "insertions": 13, "lines": 13, "dmm_unit_size": null, "dmm_unit_complexity": null, "dmm_unit_interfacing": null, "files_exts": ["adoc"], "inducing_commit_hash_pyszz": []}, {"repo_name": "spring-boot", "repo_url": "spring-projects/spring-boot", "issue_html_url": "https://github.com/spring-projects/spring-boot/issues/5692", "earliest_issue_date": "2016-04-14T16:32:00Z", "fix_commit_hash": "21bc166c95f8d7e49412644b51e9e79da2c62024", "tipo": "Commit", "commit_author": "Phillip Webb", "commiter": "Phillip Webb", "commit_date": "2016-04-14T10:38:22-07:00", "committer_data": "2016-04-14T10:38:22-07:00", "changed_files": 7, "deletions": 7, "insertions": 27, "lines": 34, "dmm_unit_size": null, "dmm_unit_complexity": null, "dmm_unit_interfacing": null, "files_exts": ["java", "java", "java", "java", "java", "java", "java"], "inducing_commit_hash_pyszz": ["81d56355715a58b511257eb79a3059477652138e"]}, {"repo_name": "spring-boot", "repo_url": "spring-projects/spring-boot", "issue_html_url": "https://github.com/spring-projects/spring-boot/issues/5683", "earliest_issue_date": "2016-04-13T18:49:14Z", "fix_commit_hash": "eb8b77e3508141a906ef467416609095000eecdb", "tipo": "Commit", "commit_author": "Andy Wilkinson", "commiter": "Andy Wilkinson", "commit_date": "2016-04-15T11:35:41+01:00", "committer_data": "2016-04-15T11:46:18+01:00", "changed_files": 4, "deletions": 24, "insertions": 120, "lines": 144, "dmm_unit_size": 1.0, "dmm_unit_complexity": 1.0, "dmm_unit_interfacing": 1.0, "files_exts": ["xml", "java", "factories", "java"], "inducing_commit_hash_pyszz": ["8d2421938bb252a6082c3ade9070ce28066fab36"]}, {"repo_name": "spring-boot", "repo_url": "spring-projects/spring-boot", "issue_html_url": "https://github.com/spring-projects/spring-boot/issues/5679", "earliest_issue_date": "2016-04-13T16:43:27Z", "fix_commit_hash": "6bbd50e084b14e1135303ea0c771eb27733fca9d", "tipo": "Commit", "commit_author": "Christian Flamm", "commiter": "Andy Wilkinson", "commit_date": "2016-04-19T12:38:56+02:00", "committer_data": "2016-05-10T16:20:33+01:00", "changed_files": 1, "deletions": 1, "insertions": 1, "lines": 2, "dmm_unit_size": null, "dmm_unit_complexity": null, "dmm_unit_interfacing": null, "files_exts": ["script"], "inducing_commit_hash_pyszz": []}, {"repo_name": "spring-boot", "repo_url": "spring-projects/spring-boot", "issue_html_url": "https://github.com/spring-projects/spring-boot/issues/5677", "earliest_issue_date": "2016-04-13T15:00:37Z", "fix_commit_hash": "959e161555a147cac812915b1677abb46e3a860b", "tipo": "Commit", "commit_author": "Madhura Bhave", "commiter": "Madhura Bhave", "commit_date": "2019-04-10T11:28:37-07:00", "committer_data": "2019-04-12T10:34:19-07:00", "changed_files": 10, "deletions": 30, "insertions": 139, "lines": 169, "dmm_unit_size": 1.0, "dmm_unit_complexity": 1.0, "dmm_unit_interfacing": 1.0, "files_exts": ["java", "java", "java", "java", "java", "java", "java", "java", "java", "adoc"], "inducing_commit_hash_pyszz": ["20b29db5123544b9c92902530d02a0d59dae670a"]}, {"repo_name": "spring-boot", "repo_url": "spring-projects/spring-boot", "issue_html_url": "https://github.com/spring-projects/spring-boot/issues/5669", "earliest_issue_date": "2016-04-12T23:33:49Z", "fix_commit_hash": "d62c26c971257d9fe4a6920508fc08209086373f", "tipo": "Commit", "commit_author": "Andy Wilkinson", "commiter": "Andy Wilkinson", "commit_date": "2017-07-27T08:44:32+01:00", "committer_data": "2017-07-27T10:18:21+01:00", "changed_files": 1, "deletions": 4, "insertions": 23, "lines": 27, "dmm_unit_size": 0.0, "dmm_unit_complexity": 0.0, "dmm_unit_interfacing": 1.0, "files_exts": ["java"], "inducing_commit_hash_pyszz": ["ffe21175ca720e40f33d9e02681b2d339dad17f3"]}, {"repo_name": "spring-boot", "repo_url": "spring-projects/spring-boot", "issue_html_url": "https://github.com/spring-projects/spring-boot/issues/5665", "earliest_issue_date": "2016-04-12T12:22:14Z", "fix_commit_hash": "1412eaa0e0eebf767047564fc476d27fcec2d05e", "tipo": "Commit", "commit_author": "Andy Wilkinson", "commiter": "Andy Wilkinson", "commit_date": "2016-04-12T13:47:58+01:00", "committer_data": "2016-04-12T13:47:58+01:00", "changed_files": 2, "deletions": 6, "insertions": 8, "lines": 14, "dmm_unit_size": 1.0, "dmm_unit_complexity": 1.0, "dmm_unit_interfacing": 1.0, "files_exts": ["java", "java"], "inducing_commit_hash_pyszz": ["5e0ba6ea2e235da76798a9b6dd55833b7951e66e"]}, {"repo_name": "spring-boot", "repo_url": "spring-projects/spring-boot", "issue_html_url": "https://github.com/spring-projects/spring-boot/issues/5657", "earliest_issue_date": "2016-04-11T15:39:00Z", "fix_commit_hash": "99ae6dac5321a741d93ff5187fafb94c295a6928", "tipo": "Commit", "commit_author": "Stephane Nicoll", "commiter": "Stephane Nicoll", "commit_date": "2016-04-11T18:23:27+02:00", "committer_data": "2016-04-11T18:23:27+02:00", "changed_files": 5, "deletions": 11, "insertions": 77, "lines": 88, "dmm_unit_size": 0.9411764705882353, "dmm_unit_complexity": 1.0, "dmm_unit_interfacing": 1.0, "files_exts": ["java", "java", "java", "adoc", "properties"], "inducing_commit_hash_pyszz": ["fa84b179a8d8a53988c7a11a0f37a9d9ab33642d"]}, {"repo_name": "spring-boot", "repo_url": "spring-projects/spring-boot", "issue_html_url": "https://github.com/spring-projects/spring-boot/issues/5653", "earliest_issue_date": "2016-04-11T10:26:06Z", "fix_commit_hash": "6574feea873afd00753abe0004724b9d6ea51b8f", "tipo": "Commit", "commit_author": "Stephane Nicoll", "commiter": "Stephane Nicoll", "commit_date": "2016-06-16T15:44:10+02:00", "committer_data": "2016-06-16T15:44:22+02:00", "changed_files": 2, "deletions": 5, "insertions": 7, "lines": 12, "dmm_unit_size": null, "dmm_unit_complexity": null, "dmm_unit_interfacing": null, "files_exts": ["adoc", "json"], "inducing_commit_hash_pyszz": []}]