[{"repo_name": "spring-boot", "repo_url": "spring-projects/spring-boot", "issue_html_url": "https://github.com/spring-projects/spring-boot/issues/3362", "earliest_issue_date": "2015-06-30T11:20:15Z", "fix_commit_hash": "5a1e66b3d620c49c9e1ad9f0ac4244444c4ea892", "tipo": "Commit", "commit_author": "Andy Wilkinson", "commiter": "Andy Wilkinson", "commit_date": "2015-06-30T12:32:29+01:00", "committer_data": "2015-06-30T12:32:29+01:00", "changed_files": 1, "deletions": 1, "insertions": 2, "lines": 3, "dmm_unit_size": null, "dmm_unit_complexity": null, "dmm_unit_interfacing": null, "files_exts": ["java"], "inducing_commit_hash_pyszz": ["69ea4beb8a08f2232bfbe891bc5c76bca26a2bef"], "inducing_commit_hash_pd": ["69ea4beb8a08f2232bfbe891bc5c76bca26a2bef"]}, {"repo_name": "spring-boot", "repo_url": "spring-projects/spring-boot", "issue_html_url": "https://github.com/spring-projects/spring-boot/issues/3360", "earliest_issue_date": "2015-06-30T08:28:56Z", "fix_commit_hash": "7410eee34f01da6d04087bf5f058c77ad85818e1", "tipo": "Commit", "commit_author": "Dave Syer", "commiter": "Dave Syer", "commit_date": "2015-07-08T15:59:03+01:00", "committer_data": "2015-07-08T15:59:05+01:00", "changed_files": 1, "deletions": 0, "insertions": 24, "lines": 24, "dmm_unit_size": 1.0, "dmm_unit_complexity": 1.0, "dmm_unit_interfacing": 1.0, "files_exts": ["java"], "inducing_commit_hash_pyszz": [], "inducing_commit_hash_pd": []}, {"repo_name": "spring-boot", "repo_url": "spring-projects/spring-boot", "issue_html_url": "https://github.com/spring-projects/spring-boot/issues/3356", "earliest_issue_date": "2015-06-29T23:17:20Z", "fix_commit_hash": "a89139c06b34c4ff893528ac1d96eb7e818c4c42", "tipo": "Commit", "commit_author": "Phillip Webb", "commiter": "Phillip Webb", "commit_date": "2015-06-30T13:49:45-07:00", "committer_data": "2015-06-30T13:49:45-07:00", "changed_files": 2, "deletions": 1, "insertions": 13, "lines": 14, "dmm_unit_size": null, "dmm_unit_complexity": null, "dmm_unit_interfacing": null, "files_exts": ["java", "java"], "inducing_commit_hash_pyszz": ["6009f417828e98b5e9b9b2b79d636fe882080326"], "inducing_commit_hash_pd": ["6009f417828e98b5e9b9b2b79d636fe882080326"]}, {"repo_name": "spring-boot", "repo_url": "spring-projects/spring-boot", "issue_html_url": "https://github.com/spring-projects/spring-boot/issues/3354", "earliest_issue_date": "2015-06-29T22:20:56Z", "fix_commit_hash": "268b7911dd1725fa71911ad32b5daf29d486b395", "tipo": "Commit", "commit_author": "Phillip Webb", "commiter": "Phillip Webb", "commit_date": "2015-06-29T17:14:44-07:00", "committer_data": "2015-06-29T17:14:44-07:00", "changed_files": 4, "deletions": 9, "insertions": 9, "lines": 18, "dmm_unit_size": null, "dmm_unit_complexity": null, "dmm_unit_interfacing": null, "files_exts": ["java", "java", "java", "adoc"], "inducing_commit_hash_pyszz": ["dd561d15cf84191f5b1731741acf3c4ee3e2f9ca"], "inducing_commit_hash_pd": ["dd561d15cf84191f5b1731741acf3c4ee3e2f9ca"]}, {"repo_name": "spring-boot", "repo_url": "spring-projects/spring-boot", "issue_html_url": "https://github.com/spring-projects/spring-boot/issues/3353", "earliest_issue_date": "2015-06-29T22:16:13Z", "fix_commit_hash": "1466169dc087bbff62124251c4255abde5f8f642", "tipo": "Commit", "commit_author": "Stephane Nicoll", "commiter": "Stephane Nicoll", "commit_date": "2015-08-20T10:33:04+02:00", "committer_data": "2015-08-20T10:33:04+02:00", "changed_files": 9, "deletions": 6, "insertions": 206, "lines": 212, "dmm_unit_size": 1.0, "dmm_unit_complexity": 1.0, "dmm_unit_interfacing": 1.0, "files_exts": ["java", "java", "java", "java", "java", "java", "java", "java", "java"], "inducing_commit_hash_pyszz": ["dd561d15cf84191f5b1731741acf3c4ee3e2f9ca"], "inducing_commit_hash_pd": ["dd561d15cf84191f5b1731741acf3c4ee3e2f9ca"]}, {"repo_name": "spring-boot", "repo_url": "spring-projects/spring-boot", "issue_html_url": "https://github.com/spring-projects/spring-boot/issues/3349", "earliest_issue_date": "2015-06-29T14:46:27Z", "fix_commit_hash": "8e78ba8ce77aa3206e3bd5be7b9291f0840f3478", "tipo": "Commit", "commit_author": "Phillip Webb", "commiter": "Phillip Webb", "commit_date": "2015-06-29T17:54:16-07:00", "committer_data": "2015-06-29T17:54:16-07:00", "changed_files": 1, "deletions": 25, "insertions": 12, "lines": 37, "dmm_unit_size": 0.0, "dmm_unit_complexity": 0.0, "dmm_unit_interfacing": 0.0, "files_exts": ["java"], "inducing_commit_hash_pyszz": ["a36d1e2eedd90040b7066cfa82c8238ae6437696"], "inducing_commit_hash_pd": ["a36d1e2eedd90040b7066cfa82c8238ae6437696", "cf24af0bfbfdd778bfb076947ea6f012a88f372d", "215689bd4dece56e7044034535edf090dda65914"]}, {"repo_name": "spring-boot", "repo_url": "spring-projects/spring-boot", "issue_html_url": "https://github.com/spring-projects/spring-boot/issues/3345", "earliest_issue_date": "2015-06-28T18:35:09Z", "fix_commit_hash": "1e464da2480568014a87dd0bac6febe63a76c889", "tipo": "Commit", "commit_author": "Dave Syer", "commiter": "Dave Syer", "commit_date": "2015-06-30T09:01:35+01:00", "committer_data": "2015-06-30T09:42:58+01:00", "changed_files": 20, "deletions": 281, "insertions": 929, "lines": 1210, "dmm_unit_size": 0.7318435754189944, "dmm_unit_complexity": 0.7262569832402235, "dmm_unit_interfacing": 0.9720670391061452, "files_exts": ["java", "java", "java", "java", "java", "java", "java", "java", "java", "factories", "java", "java", "java", "java", "java", "java", "html", "adoc", "adoc", "properties"], "inducing_commit_hash_pyszz": ["1f6ac52b961f788408a55621e3cb4ec4a345e409"], "inducing_commit_hash_pd": ["00c227ac011e3cb12e9698a049f2471389d1bdee", "772cc851a0c5c46b623b250a44266b70f69678e9", "99b3240ab270a935061b4ac68fe59053cccfcc8c", "99350a221658e2c446d0f5636d751f00747e8b88", "aaa2ff54dd09b5df9bb9cb82ccb8c4cbb230b60a", "87e00cfae9ab237e37df3f67e97eaa56957c857e", "cdf785a8d129829e657967ad7b8303bd7bdc5691", "0c2bc99af373ab9b03ab15b3bb58c57b0c3b56b7", "24e71e868f0599eb041b80d32f7cd3e17977c897", "25cc68cafec45e040d2fabf8152196f1f8f11660", "a8bf9d34d586d5defbef5ead09e558b01d0c2702", "48db5457f1060786011c0a46abea8fa9a9e05307", "f9aeb6aefe6773ab958b86e9965cf956ac0995b0", "bd26b28aa5110dd67ce2b5b5567aa14b42664e57", "c83400d265962b871c8122809fe58c22ba123aed", "a91e85b8487c0998fd9f3be03556df6a4b2e6e5b", "e96f75fdc1053da344348f7be8d32130b24d21c2", "764e34b9db567895a69ad63d6b4f73829647eb82", "b2b487ee5f5769137c7ba6372df01b7cd0908ad5", "7f1264bb65bf2b5285fe81b20006b36b226b0426", "83f842a22617ff216ec247104567675aa5f9e38b", "d854c09d5ad19648691c959768d3771b091bd231", "a3527521a25eee700a2197264b7cbd24d0ef38b2", "8628adcb7449588b38b0ffa3e80056ee97b27e4a", "1c0cce441dde23ad7060a5658c9447dfc4db9e16", "8c347fc99be62e0f8ce6413d0e830f901bc1e97b", "5d2d39e87d73c5cf975053e3c79260b2c64d3b7e", "96d479c3d95aac5eb66f9bb3656ff7e3907ed23c", "d17b7c8195477c43ea99b2508d216bb6dc4c6b65", "4c359e1a4dc40beb0914027be189c6abf0192544", "98135c964ba20b9b93f566911c3d146523024ebb", "0d583deb27a27a7ed15b5a2da3b27865a01a33f3", "36c3ceab97beeee5601b6061db904537f442a9a1", "12f0d4d95e68082e10a51230b81ebc19af0c4608", "6657e3ef840f12cb0df8b3b0cd5559862483d2c9", "bbac4ea9fb5a49c9e8e2a38f424882c6bde04789", "5dd40e69991f7507370c8a70dfc3b518f6e30c42", "0df4156b57ed69ed20f78d0db46d4e5dd35db13d", "883fd9162f375e5e4f4d03eb818d223108eeb560", "b5832622113adea64aee728e885146985daace51", "68448a8c68b05cc318b7c9e450ed389c1d3dd48a", "84d3a34c49bbbd1228189e78606b2efd7f57e276", "308a5eaff5d3d2ee53b18d456dea7b3d36429bc6", "1f6ac52b961f788408a55621e3cb4ec4a345e409", "fa507005cdf5981499a85ebcd83678d697094cea", "412b7b9e50da9eecafeecb51cefdb09fd3713828", "3eb5c348fb93a416d5dcd0003d3273570a217589", "676cacd308415ebe3df50d64d8e509a95b1c79a4"]}, {"repo_name": "spring-boot", "repo_url": "spring-projects/spring-boot", "issue_html_url": "https://github.com/spring-projects/spring-boot/issues/3343", "earliest_issue_date": "2015-06-28T08:47:35Z", "fix_commit_hash": "cc3aea2b69cbcc3b46d279a47c9a52107242c7c8", "tipo": "Commit", "commit_author": "Andy Wilkinson", "commiter": "Andy Wilkinson", "commit_date": "2015-06-29T16:52:05+01:00", "committer_data": "2015-06-29T16:52:05+01:00", "changed_files": 2, "deletions": 1, "insertions": 6, "lines": 7, "dmm_unit_size": 1.0, "dmm_unit_complexity": 1.0, "dmm_unit_interfacing": 1.0, "files_exts": ["java", "java"], "inducing_commit_hash_pyszz": ["4ede9cd1be0eb8b7edea7807e042895ce118639e"], "inducing_commit_hash_pd": ["c34cfb27a3a235a43f42988b8a6e8e0be5f44ebf"]}, {"repo_name": "spring-boot", "repo_url": "spring-projects/spring-boot", "issue_html_url": "https://github.com/spring-projects/spring-boot/issues/3338", "earliest_issue_date": "2015-06-26T20:34:19Z", "fix_commit_hash": "f3f562f3866c1c09ebac9c55e711b68a579388e5", "tipo": "Commit", "commit_author": "Phillip Webb", "commiter": "Phillip Webb", "commit_date": "2015-06-26T13:34:35-07:00", "committer_data": "2015-06-26T15:59:07-07:00", "changed_files": 19, "deletions": 56, "insertions": 476, "lines": 532, "dmm_unit_size": 0.875, "dmm_unit_complexity": 0.993421052631579, "dmm_unit_interfacing": 0.40789473684210525, "files_exts": ["xml", "java", "java", "java", "java", "java", "java", "java", "java", "java", "java", "java", "java", "java", "java", "java", "java", "xml", "xml"], "inducing_commit_hash_pyszz": ["09eed727fe39359ef52c1d5428c6a171cbb74b5d"], "inducing_commit_hash_pd": ["c3d93f70b8a4556c29e8e166edcc87b9b9e77938", "cf24af0bfbfdd778bfb076947ea6f012a88f372d", "fc2e616cc299c2527e82582d9fdcb244b9bd8698", "6391973ed05aaf34fde02f98481101269e1a25a0", "fb6b2244707dd5dfad12d62cb6a3c396555270d1", "931add4a7daffe2b255f5774af44ec1a12877d91", "bebcd60b7c81dc6069861de698fb42f32e6466ea", "09eed727fe39359ef52c1d5428c6a171cbb74b5d"]}, {"repo_name": "spring-boot", "repo_url": "spring-projects/spring-boot", "issue_html_url": "https://github.com/spring-projects/spring-boot/issues/3330", "earliest_issue_date": "2015-06-25T14:27:27Z", "fix_commit_hash": "31336c2dce34044bca9781711a7dd60c36df7508", "tipo": "Commit", "commit_author": "Andy Wilkinson", "commiter": "Andy Wilkinson", "commit_date": "2015-06-25T16:57:13+01:00", "committer_data": "2015-06-25T16:58:58+01:00", "changed_files": 1, "deletions": 2, "insertions": 29, "lines": 31, "dmm_unit_size": 0.0, "dmm_unit_complexity": 1.0, "dmm_unit_interfacing": 1.0, "files_exts": ["java"], "inducing_commit_hash_pyszz": ["4038b394960df177aee623c590f94bb8454553b6"], "inducing_commit_hash_pd": ["4038b394960df177aee623c590f94bb8454553b6"]}]