[
    {
        "repo_name": "spring-boot",
        "repo_url": "spring-projects/spring-boot",
        "issue_html_url": "https://github.com/spring-projects/spring-boot/issues/506",
        "earliest_issue_date": "2014-03-17T16:20:29Z",
        "fix_commit_hash": "7be2d97d49b89d8da1449faccc1c6b86c018f60d",
        "tipo": "Commit",
        "commit_author": "Chris Savory",
        "commiter": "Dave Syer",
        "commit_date": "2014-03-19T13:21:44-07:00",
        "committer_data": "2014-03-20T08:12:11+00:00",
        "changed_files": 3,
        "deletions": 5,
        "insertions": 26,
        "lines": 31,
        "dmm_unit_size": 1.0,
        "dmm_unit_complexity": 1.0,
        "dmm_unit_interfacing": 1.0,
        "files_exts": [
            "java",
            "java",
            "properties"
        ]
    },
    {
        "repo_name": "spring-boot",
        "repo_url": "spring-projects/spring-boot",
        "issue_html_url": "https://github.com/spring-projects/spring-boot/issues/503",
        "earliest_issue_date": "2014-03-17T06:08:34Z",
        "fix_commit_hash": "c5ee3c7ebad735a8fc67299b4c4e5e7fd776c6bf",
        "tipo": "Commit",
        "commit_author": "Phillip Webb",
        "commiter": "Phillip Webb",
        "commit_date": "2014-03-16T23:00:12-07:00",
        "committer_data": "2014-03-16T23:00:12-07:00",
        "changed_files": 24,
        "deletions": 4418,
        "insertions": 287,
        "lines": 4705,
        "dmm_unit_size": null,
        "dmm_unit_complexity": null,
        "dmm_unit_interfacing": null,
        "files_exts": [
            "adoc",
            "adoc",
            "md",
            "adoc",
            "md",
            "yml",
            "md",
            "md",
            "md",
            "md",
            "md",
            "md",
            "md",
            "md",
            "md",
            "md",
            "md",
            "md",
            "md",
            "md",
            "md",
            "md",
            "md",
            "md"
        ]
    },
    {
        "repo_name": "spring-boot",
        "repo_url": "spring-projects/spring-boot",
        "issue_html_url": "https://github.com/spring-projects/spring-boot/issues/499",
        "earliest_issue_date": "2014-03-15T19:14:38Z",
        "fix_commit_hash": "d0cd1df9789493c4936f9d9cf6a3c697d5595f2c",
        "tipo": "Commit",
        "commit_author": "Dave Syer",
        "commiter": "Dave Syer",
        "commit_date": "2014-03-18T08:37:04+00:00",
        "committer_data": "2014-03-18T08:37:04+00:00",
        "changed_files": 2,
        "deletions": 0,
        "insertions": 54,
        "lines": 54,
        "dmm_unit_size": null,
        "dmm_unit_complexity": null,
        "dmm_unit_interfacing": null,
        "files_exts": [
            "adoc",
            "adoc"
        ]
    },
    {
        "repo_name": "spring-boot",
        "repo_url": "spring-projects/spring-boot",
        "issue_html_url": "https://github.com/spring-projects/spring-boot/issues/492",
        "earliest_issue_date": "2014-03-14T16:04:31Z",
        "fix_commit_hash": "9f8c8c3fe70d3c72ebe9e74279099439bdc3bdcb",
        "tipo": "Commit",
        "commit_author": "Phillip Webb",
        "commiter": "Phillip Webb",
        "commit_date": "2014-03-17T00:07:53-07:00",
        "committer_data": "2014-03-17T00:07:53-07:00",
        "changed_files": 1,
        "deletions": 31,
        "insertions": 31,
        "lines": 62,
        "dmm_unit_size": null,
        "dmm_unit_complexity": null,
        "dmm_unit_interfacing": null,
        "files_exts": [
            "adoc"
        ]
    },
    {
        "repo_name": "spring-boot",
        "repo_url": "spring-projects/spring-boot",
        "issue_html_url": "https://github.com/spring-projects/spring-boot/issues/489",
        "earliest_issue_date": "2014-03-13T17:14:33Z",
        "fix_commit_hash": "38585bf3b64a35c2e8b43c05202cf5f7f7969261",
        "tipo": "Commit",
        "commit_author": "Andy Wilkinson",
        "commiter": "Andy Wilkinson",
        "commit_date": "2014-03-17T13:37:33+00:00",
        "committer_data": "2014-03-18T10:03:38+00:00",
        "changed_files": 5,
        "deletions": 34,
        "insertions": 45,
        "lines": 79,
        "dmm_unit_size": 0.0,
        "dmm_unit_complexity": 1.0,
        "dmm_unit_interfacing": 1.0,
        "files_exts": [
            "java",
            "java",
            "java",
            "java",
            "java"
        ]
    },
    {
        "repo_name": "spring-boot",
        "repo_url": "spring-projects/spring-boot",
        "issue_html_url": "https://github.com/spring-projects/spring-boot/issues/486",
        "earliest_issue_date": "2014-03-13T08:36:38Z",
        "fix_commit_hash": "a71c9b5de7cabd53461659faff3d133d74332579",
        "tipo": "Commit",
        "commit_author": "Dave Syer",
        "commiter": "Dave Syer",
        "commit_date": "2014-03-13T09:03:11+00:00",
        "committer_data": "2014-03-13T09:03:11+00:00",
        "changed_files": 2,
        "deletions": 1,
        "insertions": 20,
        "lines": 21,
        "dmm_unit_size": 1.0,
        "dmm_unit_complexity": 1.0,
        "dmm_unit_interfacing": 1.0,
        "files_exts": [
            "java",
            "java"
        ]
    },
    {
        "repo_name": "spring-boot",
        "repo_url": "spring-projects/spring-boot",
        "issue_html_url": "https://github.com/spring-projects/spring-boot/issues/483",
        "earliest_issue_date": "2014-03-12T15:16:18Z",
        "fix_commit_hash": "48636e3d6efe3295e3cedea8ea3c18481c1b70ec",
        "tipo": "Commit",
        "commit_author": "Dave Syer",
        "commiter": "Dave Syer",
        "commit_date": "2014-03-21T12:16:59+00:00",
        "committer_data": "2014-03-21T17:01:43+00:00",
        "changed_files": 7,
        "deletions": 71,
        "insertions": 293,
        "lines": 364,
        "dmm_unit_size": 0.06818181818181818,
        "dmm_unit_complexity": 0.38636363636363635,
        "dmm_unit_interfacing": 0.6818181818181818,
        "files_exts": [
            "adoc",
            "java",
            "java",
            "java",
            "java",
            "java",
            "java"
        ]
    },
    {
        "repo_name": "spring-boot",
        "repo_url": "spring-projects/spring-boot",
        "issue_html_url": "https://github.com/spring-projects/spring-boot/issues/482",
        "earliest_issue_date": "2014-03-12T14:44:57Z",
        "fix_commit_hash": "659d7b6df1e9d2f744b8ec51b2c0be65825ac07b",
        "tipo": "Commit",
        "commit_author": "Dave Syer",
        "commiter": "Dave Syer",
        "commit_date": "2014-03-13T09:33:29+00:00",
        "committer_data": "2014-03-13T09:33:29+00:00",
        "changed_files": 2,
        "deletions": 1,
        "insertions": 81,
        "lines": 82,
        "dmm_unit_size": 1.0,
        "dmm_unit_complexity": 1.0,
        "dmm_unit_interfacing": 1.0,
        "files_exts": [
            "java",
            "java"
        ]
    },
    {
        "repo_name": "spring-boot",
        "repo_url": "spring-projects/spring-boot",
        "issue_html_url": "https://github.com/spring-projects/spring-boot/issues/479",
        "earliest_issue_date": "2014-03-12T06:07:39Z",
        "fix_commit_hash": "14d52b6c1819c16db3e76c2634a5aba6aaa139a5",
        "tipo": "Commit",
        "commit_author": "Dave Syer",
        "commiter": "Dave Syer",
        "commit_date": "2014-03-12T09:19:00+00:00",
        "committer_data": "2014-03-12T09:21:07+00:00",
        "changed_files": 5,
        "deletions": 16,
        "insertions": 154,
        "lines": 170,
        "dmm_unit_size": 1.0,
        "dmm_unit_complexity": 1.0,
        "dmm_unit_interfacing": 1.0,
        "files_exts": [
            "java",
            "java",
            "java",
            "java",
            "java"
        ]
    },
    {
        "repo_name": "spring-boot",
        "repo_url": "spring-projects/spring-boot",
        "issue_html_url": "https://github.com/spring-projects/spring-boot/issues/473",
        "earliest_issue_date": "2014-03-11T12:29:15Z",
        "fix_commit_hash": "123457a58850be6b36e09db6195c42a462e1bb8d",
        "tipo": "Commit",
        "commit_author": "Dave Syer",
        "commiter": "Dave Syer",
        "commit_date": "2014-03-11T12:36:03+00:00",
        "committer_data": "2014-03-11T12:36:03+00:00",
        "changed_files": 3,
        "deletions": 7,
        "insertions": 139,
        "lines": 146,
        "dmm_unit_size": 0.0,
        "dmm_unit_complexity": 0.0,
        "dmm_unit_interfacing": 0.9090909090909091,
        "files_exts": [
            "java",
            "java",
            "java"
        ]
    }
]