[
    {
        "fix_commit_hash": "1bd52bc4324a1089c311ffd4adeacfabf05803c4",
        "repo_name": "spring-boot",
        "best_scenario_issue_date": "2018-07-20T18:15:56+03:00"
    },
    {
        "fix_commit_hash": "fd62eab23a8cbc3d7651df970afbaa24c9fa4774",
        "repo_name": "spring-boot",
        "best_scenario_issue_date": "2013-07-17T01:13:21-07:00"
    },
    {
        "fix_commit_hash": "a9a37f0dd581d33793e01223a4b4c2452f9f43e0",
        "repo_name": "spring-boot",
        "best_scenario_issue_date": "2021-03-26T20:15:11+01:00"
    },
    {
        "fix_commit_hash": "6075682e64ae2cb3b30db04f717358038556d9a3",
        "repo_name": "spring-boot",
        "best_scenario_issue_date": "2016-02-24T17:06:54+00:00"
    },
    {
        "fix_commit_hash": "c9f04c397793b661569b012a647926b82d5aa11b",
        "repo_name": "spring-boot",
        "best_scenario_issue_date": "2018-04-24T11:04:29+01:00"
    },
    {
        "fix_commit_hash": "1ee47cec31c4f3f72679da907216c127be094778",
        "repo_name": "spring-boot",
        "best_scenario_issue_date": "2017-09-22T23:29:30-05:00"
    },
    {
        "fix_commit_hash": "884c058e573ff3bf3824aea414f56485d514d00d",
        "repo_name": "spring-boot",
        "best_scenario_issue_date": "2014-10-31T10:19:28-07:00"
    },
    {
        "fix_commit_hash": "7736cb1dc55ee0c5b6ebdd53c5001494ec4bfe77",
        "repo_name": "spring-boot",
        "best_scenario_issue_date": "2017-07-28T11:44:28+02:00"
    },
    {
        "fix_commit_hash": "f3f119b111d21785bca0772526aeb18a2e57f2f9",
        "repo_name": "spring-boot",
        "best_scenario_issue_date": "2021-06-09T17:01:48+01:00"
    },
    {
        "fix_commit_hash": "e10ac76761206c679dd4470c516937b6922edd25",
        "repo_name": "spring-boot",
        "best_scenario_issue_date": "2023-09-20T15:44:03-07:00"
    }
]