[
    {
        "fix_commit_hash": "b1044ca8833bdb7d63d680c1cb2bba3c4223165f",
        "repo_name": "spring-boot",
        "best_scenario_issue_date": "2020-06-05T15:38:47-07:00"
    },
    {
        "fix_commit_hash": "0f85f31960b958f9a1fc32dc2a00185e96c02726",
        "repo_name": "spring-boot",
        "best_scenario_issue_date": "2013-11-16T01:23:10-08:00"
    },
    {
        "fix_commit_hash": "cfba5e836147742be9ee17321422754bfb8f5b73",
        "repo_name": "spring-boot",
        "best_scenario_issue_date": "2014-02-25T12:52:36+00:00"
    },
    {
        "fix_commit_hash": "bf7271afa59772914f1b38d650fc4ae6052fe18c",
        "repo_name": "spring-boot",
        "best_scenario_issue_date": "2017-01-04T10:47:17+01:00"
    },
    {
        "fix_commit_hash": "1db8ca60aa158a660ed872bb4cb53588cc030703",
        "repo_name": "spring-boot",
        "best_scenario_issue_date": "2021-05-14T13:59:46+01:00"
    },
    {
        "fix_commit_hash": "b97324493cdee2436720cde3ebbc7469d17d5dd3",
        "repo_name": "spring-boot",
        "best_scenario_issue_date": "2022-11-07T18:41:09-06:00"
    },
    {
        "fix_commit_hash": "961d41f6f69839ea861e58aef1ad7b203da83801",
        "repo_name": "spring-boot",
        "best_scenario_issue_date": "2017-05-08T11:32:20-07:00"
    },
    {
        "fix_commit_hash": "e7705f4f71c3a127db0ad945ca848bd78c8fca41",
        "repo_name": "spring-boot",
        "best_scenario_issue_date": "2022-03-08T13:45:28+00:00"
    },
    {
        "fix_commit_hash": "8b6cdbb9770158a874aef4eaea5ea16d4b6e0022",
        "repo_name": "spring-boot",
        "best_scenario_issue_date": "2020-05-13T17:47:37+01:00"
    },
    {
        "fix_commit_hash": "f6488c7f66cbd54a9fbeb2c719f3e65170302001",
        "repo_name": "spring-boot",
        "best_scenario_issue_date": "2014-03-23T00:12:49+01:00"
    }
]