[
    {
        "fix_commit_hash": "2ba01008bb9aedc25bff8a2f31b798b2de2cb946",
        "repo_name": "spring-boot",
        "best_scenario_issue_date": "2013-09-04T18:08:15+01:00"
    },
    {
        "fix_commit_hash": "858b092a87a272b1d0cf89ea8eda4328bb298b9a",
        "repo_name": "spring-boot",
        "best_scenario_issue_date": "2017-10-02T12:28:52+01:00"
    },
    {
        "fix_commit_hash": "c06a9771c2bd1f9a84f68e411c729f994d7b690f",
        "repo_name": "spring-boot",
        "best_scenario_issue_date": "2017-03-01T21:34:45-08:00"
    },
    {
        "fix_commit_hash": "bd5fea0d8c681073683f90070629acaebfb26f17",
        "repo_name": "spring-boot",
        "best_scenario_issue_date": "2013-05-18T16:39:48+01:00"
    },
    {
        "fix_commit_hash": "b7c0e3279e8f6cf539601a18f9b86b2a72db8cdc",
        "repo_name": "spring-boot",
        "best_scenario_issue_date": "2013-05-23T18:37:23+01:00"
    },
    {
        "fix_commit_hash": "762097ef2982d0ed807388a350ddcfa740a9078a",
        "repo_name": "spring-boot",
        "best_scenario_issue_date": "2016-01-26T16:25:24+01:00"
    },
    {
        "fix_commit_hash": "3995c16ba60bbeb1933c2233ffcab368655fb3c2",
        "repo_name": "spring-boot",
        "best_scenario_issue_date": "2015-07-06T18:40:20-05:00"
    },
    {
        "fix_commit_hash": "a77fee9f18e12b002cb633ed7d607c1e12d0e5c5",
        "repo_name": "spring-boot",
        "best_scenario_issue_date": "2014-04-21T16:48:45+02:00"
    },
    {
        "fix_commit_hash": "76ac781a65bc3d60dfe838f8cbf30eb5810f6e3b",
        "repo_name": "spring-boot",
        "best_scenario_issue_date": "2015-05-04T06:26:32-05:00"
    },
    {
        "fix_commit_hash": "38f0cf1ed2d53d6772e3dbe352e581962f9bad9c",
        "repo_name": "spring-boot",
        "best_scenario_issue_date": "2013-04-24T16:10:17+01:00"
    }
]