[
    {
        "fix_commit_hash": "33d8bfa99d0669e7aef54567e8f3ee9dae1c215b",
        "repo_name": "spring-boot",
        "best_scenario_issue_date": "2019-09-24T14:47:57+02:00"
    },
    {
        "fix_commit_hash": "98644df64dd4e2c0b72a5353418b31e083b63cd9",
        "repo_name": "spring-boot",
        "best_scenario_issue_date": "2020-04-28T10:26:25+01:00"
    },
    {
        "fix_commit_hash": "af5d765a088a1555b196ec1972f83cb5c1228e24",
        "repo_name": "spring-boot",
        "best_scenario_issue_date": "2015-11-30T15:01:44+01:00"
    },
    {
        "fix_commit_hash": "f24c92c6584a785cf77b4a6f2e15804301e7c3c1",
        "repo_name": "spring-boot",
        "best_scenario_issue_date": "2018-02-02T13:21:26-08:00"
    },
    {
        "fix_commit_hash": "65d0c07fd63390e2dcd60d3df3da09c14d29dd76",
        "repo_name": "spring-boot",
        "best_scenario_issue_date": "2016-11-22T14:04:41+00:00"
    },
    {
        "fix_commit_hash": "db79fe8b2c0598dbda340e5afc3e1fa95b167b46",
        "repo_name": "spring-boot",
        "best_scenario_issue_date": "2021-04-10T08:37:04+02:00"
    },
    {
        "fix_commit_hash": "25f68404f37f35cb95ade6b3ff46ec427375c867",
        "repo_name": "spring-boot",
        "best_scenario_issue_date": "2013-05-24T16:45:05+01:00"
    },
    {
        "fix_commit_hash": "aaae4aa3a17f068b030b2cb05d8e3a6e134c3cbd",
        "repo_name": "spring-boot",
        "best_scenario_issue_date": "2015-10-29T12:38:04+00:00"
    },
    {
        "fix_commit_hash": "5b1b03c56c650e53cb3becd6b2e47a523c1b9d8d",
        "repo_name": "spring-boot",
        "best_scenario_issue_date": "2020-10-13T22:22:20-05:00"
    },
    {
        "fix_commit_hash": "b5c435f8c450cd0a26b86826e802d98c73fd9b42",
        "repo_name": "spring-boot",
        "best_scenario_issue_date": "2015-06-30T18:47:37-07:00"
    }
]