[
    {
        "fix_commit_hash": "1975d511069af65f9d5ee609c3557fc0d9b92516",
        "repo_name": "spring-boot",
        "best_scenario_issue_date": "2018-02-06T12:57:28+00:00"
    },
    {
        "fix_commit_hash": "27a81e1463ffa5ba90190cc4855ff4d8e96acb1b",
        "repo_name": "spring-boot",
        "best_scenario_issue_date": "2016-01-13T16:23:35+00:00"
    },
    {
        "fix_commit_hash": "f84f31b47d9a81ba187b46cdf9ef90edf68050f0",
        "repo_name": "spring-boot",
        "best_scenario_issue_date": "2016-07-13T16:41:32+01:00"
    },
    {
        "fix_commit_hash": "468db03aef0f3f2c18f2faff2de5cad22c796fbb",
        "repo_name": "spring-boot",
        "best_scenario_issue_date": "2014-09-19T22:42:10-07:00"
    },
    {
        "fix_commit_hash": "4038b394960df177aee623c590f94bb8454553b6",
        "repo_name": "spring-boot",
        "best_scenario_issue_date": "2013-08-05T12:16:33-07:00"
    },
    {
        "fix_commit_hash": "2c4f88e221afa376661c474285e86f53c0dd4f0b",
        "repo_name": "spring-boot",
        "best_scenario_issue_date": "2015-11-06T17:03:12+01:00"
    },
    {
        "fix_commit_hash": "434f528e0a5810755d73be8d83e9927976ad8f97",
        "repo_name": "spring-boot",
        "best_scenario_issue_date": "2015-07-22T13:48:24+01:00"
    },
    {
        "fix_commit_hash": "0b3015e4ffe7b12db4a44c7bf49e1081f7cb5d90",
        "repo_name": "spring-boot",
        "best_scenario_issue_date": "2019-06-14T15:30:40-07:00"
    },
    {
        "fix_commit_hash": "cd441130bd7a46da412baf327d6040d638fe23a5",
        "repo_name": "spring-boot",
        "best_scenario_issue_date": "2024-05-16T17:38:44-05:00"
    },
    {
        "fix_commit_hash": "a498a7f477aa40b7eb1fdc3a469953188925749c",
        "repo_name": "spring-boot",
        "best_scenario_issue_date": "2013-11-07T12:47:27+01:00"
    }
]