[
    {
        "repo_name": "spring-boot",
        "repo_url": "spring-projects/spring-boot",
        "issue_html_url": "https://github.com/spring-projects/spring-boot/issues/22272",
        "earliest_issue_date": "2020-07-08T20:10:50Z",
        "fix_commit_hash": "6b7640ba2e6697a25d2f3846c39d0f3e35950b45",
        "tipo": "Commit",
        "commit_author": "Scott Frederick",
        "commiter": "Scott Frederick",
        "commit_date": "2020-07-08T15:10:42-05:00",
        "committer_data": "2020-07-08T15:10:42-05:00",
        "changed_files": 6,
        "deletions": 2,
        "insertions": 204,
        "lines": 206,
        "dmm_unit_size": null,
        "dmm_unit_complexity": null,
        "dmm_unit_interfacing": null,
        "files_exts": [
            "java",
            "java",
            "java",
            "factories",
            "java",
            "java"
        ]
    },
    {
        "repo_name": "spring-boot",
        "repo_url": "spring-projects/spring-boot",
        "issue_html_url": "https://github.com/spring-projects/spring-boot/issues/22270",
        "earliest_issue_date": "2020-07-08T20:01:39Z",
        "fix_commit_hash": "d5d84265f4311894ba343613a1943dd1425312b6",
        "tipo": "Commit",
        "commit_author": "Andy Wilkinson",
        "commiter": "Andy Wilkinson",
        "commit_date": "2020-07-09T09:43:11+01:00",
        "committer_data": "2020-07-09T09:43:11+01:00",
        "changed_files": 4,
        "deletions": 4,
        "insertions": 4,
        "lines": 8,
        "dmm_unit_size": null,
        "dmm_unit_complexity": null,
        "dmm_unit_interfacing": null,
        "files_exts": [
            "ci/images/spring-boot-ci-image/Dockerfile",
            "ci/images/spring-boot-jdk11-ci-image/Dockerfile",
            "ci/images/spring-boot-jdk14-ci-image/Dockerfile",
            "ci/images/spring-boot-jdk15-ci-image/Dockerfile"
        ]
    },
    {
        "repo_name": "spring-boot",
        "repo_url": "spring-projects/spring-boot",
        "issue_html_url": "https://github.com/spring-projects/spring-boot/issues/22268",
        "earliest_issue_date": "2020-07-08T20:01:27Z",
        "fix_commit_hash": "888bea5224f2a13a702d32a1a458ecbf9b516f02",
        "tipo": "Commit",
        "commit_author": "Andy Wilkinson",
        "commiter": "Andy Wilkinson",
        "commit_date": "2020-07-09T09:41:55+01:00",
        "committer_data": "2020-07-09T09:41:55+01:00",
        "changed_files": 3,
        "deletions": 3,
        "insertions": 3,
        "lines": 6,
        "dmm_unit_size": null,
        "dmm_unit_complexity": null,
        "dmm_unit_interfacing": null,
        "files_exts": [
            "ci/images/spring-boot-ci-image/Dockerfile",
            "ci/images/spring-boot-jdk11-ci-image/Dockerfile",
            "ci/images/spring-boot-jdk14-ci-image/Dockerfile"
        ]
    },
    {
        "repo_name": "spring-boot",
        "repo_url": "spring-projects/spring-boot",
        "issue_html_url": "https://github.com/spring-projects/spring-boot/issues/22265",
        "earliest_issue_date": "2020-07-08T17:00:31Z",
        "fix_commit_hash": "1f1c6fd3ea4faf0998aed093b64dc5e52976dbf2",
        "tipo": "Commit",
        "commit_author": "Andy Wilkinson",
        "commiter": "Andy Wilkinson",
        "commit_date": "2020-07-08T18:00:26+01:00",
        "committer_data": "2020-07-08T18:00:26+01:00",
        "changed_files": 1,
        "deletions": 2,
        "insertions": 2,
        "lines": 4,
        "dmm_unit_size": null,
        "dmm_unit_complexity": null,
        "dmm_unit_interfacing": null,
        "files_exts": [
            "adoc"
        ]
    },
    {
        "repo_name": "spring-boot",
        "repo_url": "spring-projects/spring-boot",
        "issue_html_url": "https://github.com/spring-projects/spring-boot/issues/22263",
        "earliest_issue_date": "2020-07-08T16:23:18Z",
        "fix_commit_hash": "3e33b6c85469d103266ec8492bd3cbd111e52237",
        "tipo": "Commit",
        "commit_author": "Andy Wilkinson",
        "commiter": "Andy Wilkinson",
        "commit_date": "2020-07-08T17:23:13+01:00",
        "committer_data": "2020-07-08T17:23:13+01:00",
        "changed_files": 3,
        "deletions": 18,
        "insertions": 29,
        "lines": 47,
        "dmm_unit_size": null,
        "dmm_unit_complexity": null,
        "dmm_unit_interfacing": null,
        "files_exts": [
            "java",
            "java",
            "java"
        ]
    },
    {
        "repo_name": "spring-boot",
        "repo_url": "spring-projects/spring-boot",
        "issue_html_url": "https://github.com/spring-projects/spring-boot/issues/22255",
        "earliest_issue_date": "2020-07-07T16:29:26Z",
        "fix_commit_hash": "9894be8f1e1d3ca520fd9cca074156529c20c677",
        "tipo": "Commit",
        "commit_author": "Andy Wilkinson",
        "commiter": "Andy Wilkinson",
        "commit_date": "2020-07-07T17:29:20+01:00",
        "committer_data": "2020-07-07T17:29:20+01:00",
        "changed_files": 3,
        "deletions": 12,
        "insertions": 14,
        "lines": 26,
        "dmm_unit_size": null,
        "dmm_unit_complexity": null,
        "dmm_unit_interfacing": null,
        "files_exts": [
            "java",
            "java",
            "java"
        ]
    },
    {
        "repo_name": "spring-boot",
        "repo_url": "spring-projects/spring-boot",
        "issue_html_url": "https://github.com/spring-projects/spring-boot/issues/22252",
        "earliest_issue_date": "2020-07-07T10:52:54Z",
        "fix_commit_hash": "247fd59422d591d949c457990822cb5a9ae26c9d",
        "tipo": "Commit",
        "commit_author": "Andy Wilkinson",
        "commiter": "Andy Wilkinson",
        "commit_date": "2020-07-07T11:52:50+01:00",
        "committer_data": "2020-07-07T11:52:50+01:00",
        "changed_files": 1,
        "deletions": 1,
        "insertions": 1,
        "lines": 2,
        "dmm_unit_size": null,
        "dmm_unit_complexity": null,
        "dmm_unit_interfacing": null,
        "files_exts": [
            "java"
        ]
    },
    {
        "repo_name": "spring-boot",
        "repo_url": "spring-projects/spring-boot",
        "issue_html_url": "https://github.com/spring-projects/spring-boot/issues/22251",
        "earliest_issue_date": "2020-07-07T10:52:38Z",
        "fix_commit_hash": "b8bc219b25b8be956405a7d546c1fc3f904b45ea",
        "tipo": "Commit",
        "commit_author": "Andy Wilkinson",
        "commiter": "Andy Wilkinson",
        "commit_date": "2020-07-07T11:52:34+01:00",
        "committer_data": "2020-07-07T11:52:34+01:00",
        "changed_files": 1,
        "deletions": 1,
        "insertions": 1,
        "lines": 2,
        "dmm_unit_size": null,
        "dmm_unit_complexity": null,
        "dmm_unit_interfacing": null,
        "files_exts": [
            "java"
        ]
    },
    {
        "repo_name": "spring-boot",
        "repo_url": "spring-projects/spring-boot",
        "issue_html_url": "https://github.com/spring-projects/spring-boot/issues/22250",
        "earliest_issue_date": "2020-07-07T10:43:20Z",
        "fix_commit_hash": "29b69bfbdfa6ce1a031f463f96a340ed056caf75",
        "tipo": "Commit",
        "commit_author": "Andy Wilkinson",
        "commiter": "Andy Wilkinson",
        "commit_date": "2020-07-07T11:43:17+01:00",
        "committer_data": "2020-07-07T11:43:17+01:00",
        "changed_files": 2,
        "deletions": 3,
        "insertions": 31,
        "lines": 34,
        "dmm_unit_size": null,
        "dmm_unit_complexity": null,
        "dmm_unit_interfacing": null,
        "files_exts": [
            "java",
            "java"
        ]
    },
    {
        "repo_name": "spring-boot",
        "repo_url": "spring-projects/spring-boot",
        "issue_html_url": "https://github.com/spring-projects/spring-boot/issues/22249",
        "earliest_issue_date": "2020-07-07T10:43:08Z",
        "fix_commit_hash": "da319f5f5988015e0acdfc1276db54a3cbaa3dc2",
        "tipo": "Commit",
        "commit_author": "Andy Wilkinson",
        "commiter": "Andy Wilkinson",
        "commit_date": "2020-07-07T11:43:03+01:00",
        "committer_data": "2020-07-07T11:43:03+01:00",
        "changed_files": 2,
        "deletions": 3,
        "insertions": 31,
        "lines": 34,
        "dmm_unit_size": null,
        "dmm_unit_complexity": null,
        "dmm_unit_interfacing": null,
        "files_exts": [
            "java",
            "java"
        ]
    }
]