[
    {
        "fix_commit_hash": "728e27d1932bd30487bf741379b90e39eaa8bcdb",
        "repo_name": "spring-boot",
        "best_scenario_issue_date": "2022-02-26T23:37:56+01:00"
    },
    {
        "fix_commit_hash": "afd357f45aad857c50ce4525bb9bc340320ccb8d",
        "repo_name": "spring-boot",
        "best_scenario_issue_date": "2015-07-06T18:06:36+02:00"
    },
    {
        "fix_commit_hash": "7bb1f7eb77c7ff28f49f4f05843be3ab6a4be136",
        "repo_name": "spring-boot",
        "best_scenario_issue_date": "2014-07-24T18:00:24+01:00"
    },
    {
        "fix_commit_hash": "3b12a5efe959f142ee44413367b36d59e097a59c",
        "repo_name": "spring-boot",
        "best_scenario_issue_date": "2021-11-29T12:25:04-06:00"
    },
    {
        "fix_commit_hash": "0069e41c29382a788a3515937a6a14a9b71c9107",
        "repo_name": "spring-boot",
        "best_scenario_issue_date": "2015-10-09T12:25:43+01:00"
    },
    {
        "fix_commit_hash": "c4750fd0ff971d09a6c2ce79aad401f0985b5f4e",
        "repo_name": "spring-boot",
        "best_scenario_issue_date": "2021-04-12T15:15:55+01:00"
    },
    {
        "fix_commit_hash": "0fcc52ccaf4621947b422cf58e8453321ef640f9",
        "repo_name": "spring-boot",
        "best_scenario_issue_date": "2021-01-27T14:18:41-08:00"
    },
    {
        "fix_commit_hash": "370501f4a940b2044e9be07505bbf8d84ff9ba1e",
        "repo_name": "spring-boot",
        "best_scenario_issue_date": "2013-12-15T10:07:27+00:00"
    },
    {
        "fix_commit_hash": "aa1954717cce4786e056153868a334054cd51a01",
        "repo_name": "spring-boot",
        "best_scenario_issue_date": "2019-11-01T19:11:19-07:00"
    },
    {
        "fix_commit_hash": "aa49468171d991845b20f744f17c9a06f6f24052",
        "repo_name": "spring-boot",
        "best_scenario_issue_date": "2017-02-09T10:44:03+01:00"
    }
]