[
    {
        "repo_name": "spring-boot",
        "repo_url": "spring-projects/spring-boot",
        "issue_html_url": "https://github.com/spring-projects/spring-boot/issues/22511",
        "earliest_issue_date": "2020-07-22T19:35:32Z",
        "fix_commit_hash": "d9c34d5b840e4d052a8bc0d52a5ec2a065becb3d",
        "tipo": "Commit",
        "commit_author": "Stephane Nicoll",
        "commiter": "Stephane Nicoll",
        "commit_date": "2020-07-22T21:35:48+02:00",
        "committer_data": "2020-07-22T21:35:48+02:00",
        "changed_files": 1,
        "deletions": 1,
        "insertions": 1,
        "lines": 2,
        "dmm_unit_size": null,
        "dmm_unit_complexity": null,
        "dmm_unit_interfacing": null,
        "files_exts": [
            "xml"
        ]
    },
    {
        "repo_name": "spring-boot",
        "repo_url": "spring-projects/spring-boot",
        "issue_html_url": "https://github.com/spring-projects/spring-boot/issues/22505",
        "earliest_issue_date": "2020-07-22T09:39:43Z",
        "fix_commit_hash": "0440a9a78cb0bda9132594b32835ecfdf3b208eb",
        "tipo": "Commit",
        "commit_author": "Stephane Nicoll",
        "commiter": "Stephane Nicoll",
        "commit_date": "2020-07-23T10:55:47+02:00",
        "committer_data": "2020-07-23T10:55:47+02:00",
        "changed_files": 3,
        "deletions": 6,
        "insertions": 2,
        "lines": 8,
        "dmm_unit_size": null,
        "dmm_unit_complexity": null,
        "dmm_unit_interfacing": null,
        "files_exts": [
            "yaml",
            "groovy",
            "xml"
        ]
    },
    {
        "repo_name": "spring-boot",
        "repo_url": "spring-projects/spring-boot",
        "issue_html_url": "https://github.com/spring-projects/spring-boot/issues/22503",
        "earliest_issue_date": "2020-07-22T08:50:14Z",
        "fix_commit_hash": "31042bfc4980610b2b6bc3af4f66b7a2625a330d",
        "tipo": "Commit",
        "commit_author": "Andy Wilkinson",
        "commiter": "Andy Wilkinson",
        "commit_date": "2020-11-10T13:59:23+00:00",
        "committer_data": "2020-11-10T17:35:04+00:00",
        "changed_files": 5,
        "deletions": 0,
        "insertions": 117,
        "lines": 117,
        "dmm_unit_size": 1.0,
        "dmm_unit_complexity": 1.0,
        "dmm_unit_interfacing": 1.0,
        "files_exts": [
            "xml",
            "jar",
            "java",
            "html",
            "groovy"
        ]
    },
    {
        "repo_name": "spring-boot",
        "repo_url": "spring-projects/spring-boot",
        "issue_html_url": "https://github.com/spring-projects/spring-boot/issues/22502",
        "earliest_issue_date": "2020-07-22T07:27:37Z",
        "fix_commit_hash": "b98c3dccfd4b690d61cff12c5daa6cbd400fa908",
        "tipo": "Commit",
        "commit_author": "Andy Wilkinson",
        "commiter": "Andy Wilkinson",
        "commit_date": "2020-07-27T10:47:14+01:00",
        "committer_data": "2020-07-27T10:47:14+01:00",
        "changed_files": 2,
        "deletions": 41,
        "insertions": 72,
        "lines": 113,
        "dmm_unit_size": 0.9166666666666666,
        "dmm_unit_complexity": 1.0,
        "dmm_unit_interfacing": 1.0,
        "files_exts": [
            "java",
            "java"
        ]
    },
    {
        "repo_name": "spring-boot",
        "repo_url": "spring-projects/spring-boot",
        "issue_html_url": "https://github.com/spring-projects/spring-boot/issues/22498",
        "earliest_issue_date": "2020-07-22T06:33:15Z",
        "fix_commit_hash": "44f18362d388fadfc2c90c1f7b46cf20d24adc96",
        "tipo": "Commit",
        "commit_author": "Phillip Webb",
        "commiter": "Phillip Webb",
        "commit_date": "2020-07-13T21:42:38-07:00",
        "committer_data": "2020-07-22T21:00:14-07:00",
        "changed_files": 2,
        "deletions": 1,
        "insertions": 58,
        "lines": 59,
        "dmm_unit_size": 1.0,
        "dmm_unit_complexity": 1.0,
        "dmm_unit_interfacing": 1.0,
        "files_exts": [
            "java",
            "java"
        ]
    },
    {
        "repo_name": "spring-boot",
        "repo_url": "spring-projects/spring-boot",
        "issue_html_url": "https://github.com/spring-projects/spring-boot/issues/22497",
        "earliest_issue_date": "2020-07-22T06:28:37Z",
        "fix_commit_hash": "3352024b1ca641fa0beaaa4cd87788c190242eb0",
        "tipo": "Commit",
        "commit_author": "Phillip Webb",
        "commiter": "Phillip Webb",
        "commit_date": "2020-07-13T21:19:10-07:00",
        "committer_data": "2020-07-22T21:02:32-07:00",
        "changed_files": 96,
        "deletions": 168,
        "insertions": 8130,
        "lines": 8298,
        "dmm_unit_size": 0.8708671241422333,
        "dmm_unit_complexity": 0.9569557080474111,
        "dmm_unit_interfacing": 0.8558951965065502,
        "files_exts": [
            "java",
            "java",
            "java",
            "java",
            "java",
            "java",
            "java",
            "java",
            "java",
            "java",
            "java",
            "java",
            "java",
            "java",
            "java",
            "java",
            "java",
            "java",
            "java",
            "java",
            "java",
            "java",
            "java",
            "java",
            "java",
            "java",
            "java",
            "java",
            "java",
            "java",
            "java",
            "java",
            "java",
            "java",
            "java",
            "java",
            "java",
            "java",
            "java",
            "java",
            "java",
            "json",
            "factories",
            "java",
            "java",
            "java",
            "java",
            "java",
            "java",
            "java",
            "java",
            "java",
            "java",
            "java",
            "java",
            "java",
            "java",
            "java",
            "java",
            "java",
            "java",
            "java",
            "java",
            "java",
            "java",
            "java",
            "java",
            "java",
            "java",
            "java",
            "java",
            "java",
            "java",
            "java",
            "java",
            "java",
            "yml",
            "yml",
            "yml",
            "yml",
            "yml",
            "yml",
            "properties",
            "other",
            "properties",
            "properties",
            "yml",
            "yml",
            "properties",
            "properties",
            "properties",
            "properties",
            "properties",
            "properties",
            "properties",
            "yml"
        ]
    },
    {
        "repo_name": "spring-boot",
        "repo_url": "spring-projects/spring-boot",
        "issue_html_url": "https://github.com/spring-projects/spring-boot/issues/22496",
        "earliest_issue_date": "2020-07-22T06:15:04Z",
        "fix_commit_hash": "039fbdfa7cb396127c7d0e84be86d70d22c50e6a",
        "tipo": "Commit",
        "commit_author": "Phillip Webb",
        "commiter": "Phillip Webb",
        "commit_date": "2020-07-13T21:17:46-07:00",
        "committer_data": "2020-07-22T20:58:31-07:00",
        "changed_files": 6,
        "deletions": 14,
        "insertions": 331,
        "lines": 345,
        "dmm_unit_size": 0.7195121951219512,
        "dmm_unit_complexity": 1.0,
        "dmm_unit_interfacing": 0.9512195121951219,
        "files_exts": [
            "java",
            "java",
            "java",
            "java",
            "java",
            "java"
        ]
    },
    {
        "repo_name": "spring-boot",
        "repo_url": "spring-projects/spring-boot",
        "issue_html_url": "https://github.com/spring-projects/spring-boot/issues/22495",
        "earliest_issue_date": "2020-07-22T06:09:59Z",
        "fix_commit_hash": "9e9eb90d09395ece06a9c699e8208f55bb7bf021",
        "tipo": "Commit",
        "commit_author": "Madhura Bhave",
        "commiter": "Phillip Webb",
        "commit_date": "2020-07-21T20:11:17-07:00",
        "committer_data": "2020-07-22T20:58:24-07:00",
        "changed_files": 7,
        "deletions": 63,
        "insertions": 203,
        "lines": 266,
        "dmm_unit_size": 0.7848101265822784,
        "dmm_unit_complexity": 0.5443037974683544,
        "dmm_unit_interfacing": 1.0,
        "files_exts": [
            "java",
            "java",
            "java",
            "java",
            "properties",
            "properties",
            "properties"
        ]
    },
    {
        "repo_name": "spring-boot",
        "repo_url": "spring-projects/spring-boot",
        "issue_html_url": "https://github.com/spring-projects/spring-boot/issues/22494",
        "earliest_issue_date": "2020-07-22T06:04:37Z",
        "fix_commit_hash": "945e5b92224ce58146a8f20c69f0a7f888860f7e",
        "tipo": "Commit",
        "commit_author": "Phillip Webb",
        "commiter": "Phillip Webb",
        "commit_date": "2020-07-13T21:54:54-07:00",
        "committer_data": "2020-07-22T20:57:43-07:00",
        "changed_files": 3,
        "deletions": 3,
        "insertions": 66,
        "lines": 69,
        "dmm_unit_size": 1.0,
        "dmm_unit_complexity": 1.0,
        "dmm_unit_interfacing": 1.0,
        "files_exts": [
            "java",
            "java",
            "java"
        ]
    },
    {
        "repo_name": "spring-boot",
        "repo_url": "spring-projects/spring-boot",
        "issue_html_url": "https://github.com/spring-projects/spring-boot/issues/22493",
        "earliest_issue_date": "2020-07-22T06:02:19Z",
        "fix_commit_hash": "078e14698373b9093d9637713fa36614e210a1ce",
        "tipo": "Commit",
        "commit_author": "Phillip Webb",
        "commiter": "Phillip Webb",
        "commit_date": "2020-06-23T16:50:00-07:00",
        "committer_data": "2020-07-22T20:57:43-07:00",
        "changed_files": 3,
        "deletions": 0,
        "insertions": 22,
        "lines": 22,
        "dmm_unit_size": 0.0,
        "dmm_unit_complexity": 0.0,
        "dmm_unit_interfacing": 0.0,
        "files_exts": [
            "java",
            "java",
            "yml"
        ]
    }
]